{
    "Q0-1": {
        "estado": "disponible",
        "cirugias": {
            "2026-01-22": [
                {
                    "nombre": "pepe",
                    "sesion": "Mañana (8:00)",
                    "recursos": {}
                },
                {
                    "nombre": "pepe",
                    "sesion": "Tarde (14:00)",
                    "recursos": {}
                }
            ],
            "2026-01-24": [
                {
                    "nombre": "cuco",
                    "sesion": "Mañana (8:00)",
                    "recursos": {}
                }
            ]
        }
    },
    "Q0-2": {
        "estado": "disponible",
        "cirugias": {
            "2026-01-22": [
                {
                    "nombre": "pepe",
                    "sesion": "Tarde (14:00)",
                    "recursos": {}
                },
                {
                    "nombre": "pepe",
                    "sesion": "Mañana (8:00)",
                    "recursos": {}
                }
            ]
        }
    }
}